[
    {   
        "id": 1,
        "name": "Python",
        "order": 1,
        "cohort_id": 1,
        "start_date": "01/01/2018",
        "end_date": "03/11/2018",
        "enrolled_students": [
            1,
            2,
            3,
            4,
            5,
            6,
            7,
            8,
            9,
            10
        ]
    },
    {   
        "id": 2,
        "name": "SQL",
        "order": 2,
        "cohort_id": 1,
        "start_date": "03/11/2021",
        "end_date": "06/11/2018",
        "enrolled_students": [
            1,
            2,
            3,
            4,
            7,
            8,
            9,
            10
        ]
    },
    {   
        "id": 3,
        "name": "Java",
        "order": 3,
        "cohort_id": 1,
        "start_date": "06/11/2018",
        "end_date": "08/15/2018",
        "enrolled_students": [
            1,
            2,
            3,
            4,
            7,
            8,
            10
        ]
    },
    {   
        "id": 5,
        "name": "JavaScript",
        "order": 1,
        "cohort_id": 2,
        "start_date": "09/01/2019",
        "end_date": "12/17/2019",
        "enrolled_students": [
            200,
            203,
            204,
            205,
            206,
            207,
            209,
            210
        ]
    },
    {   
        "id": 6,
        "name": "Java",
        "order": 2,
        "cohort_id": 2,
        "start_date": "01/11/2020",
        "end_date": "04/15/2020",
        "enrolled_students": [
            200,
            203,
            204,
            205,
            206,
            207,
            209,
            210
        ]
    },
    {   
        "id": 12,
        "name": "JavaScript",
        "order": 1,
        "cohort_id": 3,
        "start_date": "01/11/2021",
        "end_date": "04/15/2021",
        "enrolled_students": [
            300,
            301,
            302,
            303,
            304,
            305,
            306,
            307,
            308,
            309,
            310
        ]
    },
    {   
        "id": 13,
        "name": "Java",
        "order": 2,
        "cohort_id": 3,
        "start_date": "04/15/2021",
        "end_date": "08/15/2021",
        "enrolled_students": [
            300,
            303,
            304,
            305,
            306,
            307,
            309,
            310
        ]
    }
]